{
    "__Fields": {
        "<IsExtanalInvite>k__BackingField": false,
        "<IsInviting>k__BackingField": false,
        "<IsTryLogin>k__BackingField": false,
        "<IsValid>k__BackingField": true,
        "Setting": {
            "__Fields": {
                "InviteCodeList": {
                    "Items": [
                        {
                            "__Fields": {
                                "Code": "ja-JP",
                                "Language": 0
                            },
                            "__Methods": [
                                ".ctor (Args: 0)"
                            ],
                            "__Type": "app.udInviteManagerSettingUserData.InviteCode"
                        },
                        {
                            "__Fields": {
                                "Code": "en-US",
                                "Language": 1
                            },
                            "__Methods": [
                                ".ctor (Args: 0)"
                            ],
                            "__Type": "app.udInviteManagerSettingUserData.InviteCode"
                        },
                        {
                            "__Fields": {
                                "Code": "fr-FR",
                                "Language": 2
                            },
                            "__Methods": [
                                ".ctor (Args: 0)"
                            ],
                            "__Type": "app.udInviteManagerSettingUserData.InviteCode"
                        },
                        {
                            "__Fields": {
                                "Code": "de-DE",
                                "Language": 4
                            },
                            "__Methods": [
                                ".ctor (Args: 0)"
                            ],
                            "__Type": "app.udInviteManagerSettingUserData.InviteCode"
                        },
                        {
                            "__Fields": {
                                "Code": "it-IT",
                                "Language": 3
                            },
                            "__Methods": [
                                ".ctor (Args: 0)"
                            ],
                            "__Type": "app.udInviteManagerSettingUserData.InviteCode"
                        },
                        {
                            "__Fields": {
                                "Code": "es-ES",
                                "Language": 5
                            },
                            "__Methods": [
                                ".ctor (Args: 0)"
                            ],
                            "__Type": "app.udInviteManagerSettingUserData.InviteCode"
                        },
                        {
                            "__Fields": {
                                "Code": "ru-RU",
                                "Language": 6
                            },
                            "__Methods": [
                                ".ctor (Args: 0)"
                            ],
                            "__Type": "app.udInviteManagerSettingUserData.InviteCode"
                        },
                        {
                            "__Fields": {
                                "Code": "pl-PL",
                                "Language": 7
                            },
                            "__Methods": [
                                ".ctor (Args: 0)"
                            ],
                            "__Type": "app.udInviteManagerSettingUserData.InviteCode"
                        },
                        {
                            "__Fields": {
                                "Code": "pt-BR",
                                "Language": 10
                            },
                            "__Methods": [
                                ".ctor (Args: 0)"
                            ],
                            "__Type": "app.udInviteManagerSettingUserData.InviteCode"
                        },
                        {
                            "__Fields": {
                                "Code": "ko-KR",
                                "Language": 11
                            },
                            "__Methods": [
                                ".ctor (Args: 0)"
                            ],
                            "__Type": "app.udInviteManagerSettingUserData.InviteCode"
                        },
                        {
                            "__Fields": {
                                "Code": "zh-Hant",
                                "Language": 12
                            },
                            "__Methods": [
                                ".ctor (Args: 0)"
                            ],
                            "__Type": "app.udInviteManagerSettingUserData.InviteCode"
                        },
                        {
                            "__Fields": {
                                "Code": "zh-Hans",
                                "Language": 13
                            },
                            "__Methods": [
                                ".ctor (Args: 0)"
                            ],
                            "__Type": "app.udInviteManagerSettingUserData.InviteCode"
                        },
                        {
                            "__Fields": {
                                "Code": "ar-AE",
                                "Language": 21
                            },
                            "__Methods": [
                                ".ctor (Args: 0)"
                            ],
                            "__Type": "app.udInviteManagerSettingUserData.InviteCode"
                        },
                        {
                            "__Fields": {
                                "Code": "es-419",
                                "Language": 32
                            },
                            "__Methods": [
                                ".ctor (Args: 0)"
                            ],
                            "__Type": "app.udInviteManagerSettingUserData.InviteCode"
                        }
                    ],
                    "__Count": 14,
                    "__Fields": {
                        "_items": {
                            "Items": [
                                "<Circular>",
                                "<Circular>",
                                "<Circular>",
                                "<Circular>",
                                "<Circular>",
                                "<Circular>",
                                "<Circular>",
                                "<Circular>",
                                "<Circular>",
                                "<Circular>",
                                "<Circular>",
                                "<Circular>",
                                "<Circular>",
                                "<Circular>"
                            ],
                            "__Count": 14,
                            "__Methods": [
                                "Set (Args: 2)",
                                "Get (Args: 1)",
                                "Address (Args: 1)",
                                "GetEnumerator (Args: 0)",
                                "Add (Args: 1)",
                                "Clear (Args: 0)",
                                "Contains (Args: 1)",
                                "CopyTo (Args: 2)",
                                "Remove (Args: 1)",
                                "get_Item (Args: 1)",
                                "set_Item (Args: 2)",
                                "IndexOf (Args: 1)",
                                "Insert (Args: 2)",
                                "RemoveAt (Args: 1)"
                            ],
                            "__Type": "app.udInviteManagerSettingUserData.InviteCode[]"
                        },
                        "_size": 14,
                        "_version": 0
                    },
                    "__Methods": [
                        ".ctor (Args: 0)",
                        ".ctor (Args: 1)",
                        ".ctor (Args: 1)",
                        "get_Capacity (Args: 0)",
                        "set_Capacity (Args: 1)",
                        "get_Count (Args: 0)",
                        "System.Collections.ICollection.get_SyncRoot (Args: 0)",
                        "get_Item (Args: 1)",
                        "set_Item (Args: 2)",
                        "IsCompatibleObject (Args: 1)",
                        "System.Collections.IList.get_Item (Args: 1)",
                        "System.Collections.IList.set_Item (Args: 2)",
                        "Add (Args: 1)",
                        "AddWithResize (Args: 1)",
                        "System.Collections.IList.Add (Args: 1)",
                        "AddRange (Args: 1)",
                        "AsReadOnly (Args: 0)",
                        "BinarySearch (Args: 4)",
                        "BinarySearch (Args: 1)",
                        "BinarySearch (Args: 2)",
                        "Clear (Args: 0)",
                        "Contains (Args: 1)",
                        "System.Collections.IList.Contains (Args: 1)",
                        "CopyTo (Args: 1)",
                        "System.Collections.ICollection.CopyTo (Args: 2)",
                        "CopyTo (Args: 4)",
                        "CopyTo (Args: 2)",
                        "EnsureCapacity (Args: 1)",
                        "Exists (Args: 1)",
                        "Find (Args: 1)",
                        "FindAll (Args: 1)",
                        "FindIndex (Args: 1)",
                        "FindIndex (Args: 2)",
                        "FindIndex (Args: 3)",
                        "FindLast (Args: 1)",
                        "FindLastIndex (Args: 1)",
                        "FindLastIndex (Args: 2)",
                        "FindLastIndex (Args: 3)",
                        "ForEach (Args: 1)",
                        "GetEnumerator (Args: 0)",
                        "System.Collections.Generic.IEnumerable<T>.GetEnumerator (Args: 0)",
                        "System.Collections.IEnumerable.GetEnumerator (Args: 0)",
                        "GetRange (Args: 2)",
                        "IndexOf (Args: 1)",
                        "System.Collections.IList.IndexOf (Args: 1)",
                        "IndexOf (Args: 2)",
                        "IndexOf (Args: 3)",
                        "Insert (Args: 2)",
                        "System.Collections.IList.Insert (Args: 2)",
                        "InsertRange (Args: 2)",
                        "LastIndexOf (Args: 1)",
                        "LastIndexOf (Args: 2)",
                        "LastIndexOf (Args: 3)",
                        "Remove (Args: 1)",
                        "System.Collections.IList.Remove (Args: 1)",
                        "RemoveAll (Args: 1)",
                        "RemoveAt (Args: 1)",
                        "RemoveRange (Args: 2)",
                        "Reverse (Args: 0)",
                        "Reverse (Args: 2)",
                        "Sort (Args: 0)",
                        "Sort (Args: 1)",
                        "Sort (Args: 3)",
                        "Sort (Args: 1)",
                        "ToArray (Args: 0)",
                        "TrimExcess (Args: 0)",
                        "TrueForAll (Args: 1)",
                        ".cctor (Args: 0)"
                    ],
                    "__Type": "System.Collections.Generic.List`1<app.udInviteManagerSettingUserData.InviteCode>"
                },
                "InviteMessage": {
                    "__Fields": {
                        "mData1": 4241208419,
                        "mData2": 60778,
                        "mData3": 16386,
                        "mData4L": 2777005288953168555,
                        "mData4_0": 171,
                        "mData4_1": 66,
                        "mData4_2": 111,
                        "mData4_3": 219,
                        "mData4_4": 152,
                        "mData4_5": 231,
                        "mData4_6": 137,
                        "mData4_7": 38
                    },
                    "__Methods": [
                        "ToByteArray (Args: 0)",
                        "ToString (Args: 1)",
                        "ToString (Args: 2)",
                        "ToString (Args: 0)",
                        "Equals (Args: 1)",
                        ".ctor (Args: 1)",
                        ".ctor (Args: 1)",
                        ".ctor (Args: 4)",
                        ".ctor (Args: 11)",
                        ".ctor (Args: 11)",
                        "op_Equality (Args: 2)",
                        "op_Inequality (Args: 2)",
                        "op_LessThan (Args: 2)",
                        "op_GreaterThan (Args: 2)",
                        "Equals (Args: 1)",
                        "GetHashCode (Args: 0)",
                        "CompareTo (Args: 1)",
                        "CompareTo (Args: 1)",
                        "NewGuid (Args: 0)",
                        "Parse (Args: 1)"
                    ],
                    "__Type": "System.Guid"
                }
            },
            "__Methods": [
                ".ctor (Args: 0)"
            ],
            "__Type": "app.udInviteManagerSettingUserData"
        }
    },
    "__Methods": [
        "get_IsValid (Args: 0)",
        "set_IsValid (Args: 1)",
        "get_IsInviting (Args: 0)",
        "set_IsInviting (Args: 1)",
        "get_IsJoinSession (Args: 0)",
        "get_IsExtanalInvite (Args: 0)",
        "set_IsExtanalInvite (Args: 1)",
        "get_IsTryLogin (Args: 0)",
        "set_IsTryLogin (Args: 1)",
        "RequestCreateSession (Args: 4)",
        "RequestJoinSession (Args: 1)",
        "RequestJoinSession (Args: 2)",
        "RequestInvite (Args: 1)",
        "RequestInvite (Args: 2)",
        "RequestLeaveSession (Args: 0)",
        "RequesExternalInvite (Args: 3)",
        "FinishInviting (Args: 0)",
        "TryLogin (Args: 0)",
        "SetSessionParam (Args: 2)",
        "GetSessionParam (Args: 0)",
        "UpdateFlow (Args: 0)",
        "IsInviteRequest (Args: 0)",
        "GetInviteCode (Args: 1)",
        "GetInviteMessage (Args: 1)",
        "doStart (Args: 0)",
        "doOnDestroy (Args: 0)",
        ".ctor (Args: 0)"
    ],
    "__Type": "app.InviteManager"
}